element/__init__.py
element/element_api.py
element/parsers.py
element/py.typed
element/schemas.py
element_iot_api-1.0.2.dist-info/licenses/LICENSE
element_iot_api-1.0.2.dist-info/licenses/LICENSE.decentlab
element_iot_api-1.0.2.dist-info/METADATA
element_iot_api-1.0.2.dist-info/WHEEL
element_iot_api-1.0.2.dist-info/top_level.txt
element_iot_api-1.0.2.dist-info/RECORD
