Metadata-Version: 2.4
Name: element-iot-api
Version: 1.0.2
Summary: library to interact with the element IoT platform
Author-email: D2R-Team <climate@rub.de>
Maintainer-email: Jonas Kittner <jonas.kittner@rub.de>
License-Expression: MIT
Project-URL: Homepage, https://github.com/RUBclim/element-iot-api
Project-URL: Documentation, https://rubclim.github.io/element-iot-api/
Project-URL: Repository, https://github.com/RUBclim/element-iot-api
Classifier: Programming Language :: Python :: 3
Classifier: Programming Language :: Python :: 3 :: Only
Classifier: Programming Language :: Python :: Implementation :: CPython
Requires-Python: >=3.11
License-File: LICENSE
License-File: LICENSE.decentlab
Requires-Dist: pandas
Dynamic: license-file
